pricetag/__init__.py
pricetag/extractor.py
pricetag/normalizer.py
pricetag/patterns.py
pricetag/types.py
pricetag/validators.py
pricetag-1.0.0.dist-info/licenses/LICENSE
pricetag-1.0.0.dist-info/METADATA
pricetag-1.0.0.dist-info/WHEEL
pricetag-1.0.0.dist-info/top_level.txt
pricetag-1.0.0.dist-info/RECORD
