Metadata-Version: 2.4
Name: pricetag
Version: 1.0.0
Summary: A pure-Python library for extracting price and currency information from unstructured text
Author-email: Michelle Pellon <mgracepellon@gmail.com>
Maintainer-email: Michelle Pellon <mgracepellon@gmail.com>
License-Expression: MIT
Project-URL: Homepage, https://github.com/michellepellon/pricetag
Project-URL: Repository, https://github.com/michellepellon/pricetag
Project-URL: Documentation, https://github.com/michellepellon/pricetag#readme
Keywords: price extraction,salary parsing,text processing,nlp,compensation,job postings,data extraction
Classifier: Development Status :: 4 - Beta
Classifier: Intended Audience :: Developers
Classifier: Intended Audience :: Science/Research
Classifier: Operating System :: OS Independent
Classifier: Programming Language :: Python :: 3
Classifier: Programming Language :: Python :: 3.13
Classifier: Programming Language :: Python :: 3 :: Only
Classifier: Topic :: Text Processing
Classifier: Topic :: Text Processing :: Linguistic
Classifier: Topic :: Software Development :: Libraries :: Python Modules
Classifier: Typing :: Typed
Requires-Python: >=3.13
License-File: LICENSE
Provides-Extra: dev
Requires-Dist: pytest>=7.0.0; extra == "dev"
Requires-Dist: black>=23.0.0; extra == "dev"
Requires-Dist: mypy>=1.0.0; extra == "dev"
Requires-Dist: ruff>=0.1.0; extra == "dev"
Dynamic: license-file
